{
   "healthOnStart":5,
   "energyOnStart":100,
   "enemiesWave":[
	  {
		 "count":8,
		 "reward": 30,
		 "scenes": [
		 	"res://scenes/enemies/SpiderEnemy.tscn",
		 	"res://scenes/enemies/CiclopeEnemy.tscn",
		 	"res://scenes/enemies/EggEnemy.tscn"
		  ]
	  },
	  {
		 "count":8,
		 "reward": 30,
		 "scenes": [
		 	"res://scenes/enemies/SpiderEnemy.tscn",
		 	"res://scenes/enemies/CiclopeEnemy.tscn",
		 	"res://scenes/enemies/EggEnemy.tscn"
		  ]
	  },
	  {
		 "count":8,
		 "reward": 30,
		 "scenes": [
		 	"res://scenes/enemies/SpiderEnemy.tscn",
		 	"res://scenes/enemies/CiclopeEnemy.tscn",
		 	"res://scenes/enemies/EggEnemy.tscn",
		 	"res://scenes/enemies/ScarabEnemy.tscn"
		  ]
	  },
	  {
		 "count":5,
		 "reward": 30,
		 "scenes": [
		 	"res://scenes/enemies/SpiderEnemy.tscn",
		 	"res://scenes/enemies/ArahnaEnemy.tscn"
		  ]
	  },
	  {
		 "count":5,
		 "reward": 0,
		 "scenes": [
		 	"res://scenes/enemies/ArahnaBoss.tscn"
		  ]
	  }
   ]
}
